measure_resources/__init__.py
measure_resources/main.py
measure_resources-0.1.2.dist-info/METADATA
measure_resources-0.1.2.dist-info/WHEEL
measure_resources-0.1.2.dist-info/licenses/LICENSE
measure_resources-0.1.2.dist-info/RECORD
